
{
    "Connected": true,
    "Room": "https://falgsc.eu.org/#/pocPJ/190",
    "StatsArray": [
        {
            "candidate-pair": {
                "CPDWvHPefM_CIqR60N3": {
                    "id": "CPDWvHPefM_CIqR60N3",
                    "timestamp": "1690906102272",
                    "localCandidateId": "IDWvHPefM",
                    "remoteCandidateId": "ICIqR60N3",
                    "state": "waiting",
                    "priority": "7241540810645060608",
                    "nominated": "false",
                    "bytesSent": "0",
                    "currentRoundTripTime": "NA",
                    "totalRoundTripTime": "0",
                    "bytesReceived": "0"
                },
                "CPDWvHPefM_b2xncI1j": {
                    "id": "CPDWvHPefM_b2xncI1j",
                    "timestamp": "1690906102272",
                    "localCandidateId": "IDWvHPefM",
                    "remoteCandidateId": "Ib2xncI1j",
                    "state": "succeeded",
                    "priority": "9115038255631186944",
                    "nominated": "true",
                    "bytesSent": "105988",
                    "currentRoundTripTime": "0.001",
                    "totalRoundTripTime": "0.007",
                    "bytesReceived": "56109"
                }
            },
            "codec": {
                "CIT01_111_minptime=10;useinbandfec=1": {
                    "id": "CIT01_111_minptime=10;useinbandfec=1",
                    "timestamp": "1690906102272",
                    "payloadType": "111",
                    "clockRate": "48000",
                    "channels": "2",
                    "codecType": "NA",
                    "mimeType": "audio/opus",
                    "sdpFmtpLine": "minptime=10;useinbandfec=1"
                },
                "CIT01_96": {
                    "id": "CIT01_96",
                    "timestamp": "1690906102272",
                    "payloadType": "96",
                    "clockRate": "90000",
                    "channels": "NA",
                    "codecType": "NA",
                    "mimeType": "video/VP8",
                    "sdpFmtpLine": "NA"
                },
                "COT01_111_minptime=10;useinbandfec=1": {
                    "id": "COT01_111_minptime=10;useinbandfec=1",
                    "timestamp": "1690906102272",
                    "payloadType": "111",
                    "clockRate": "48000",
                    "channels": "2",
                    "codecType": "NA",
                    "mimeType": "audio/opus",
                    "sdpFmtpLine": "minptime=10;useinbandfec=1"
                },
                "COT01_96": {
                    "id": "COT01_96",
                    "timestamp": "1690906102272",
                    "payloadType": "96",
                    "clockRate": "90000",
                    "channels": "NA",
                    "codecType": "NA",
                    "mimeType": "video/VP8",
                    "sdpFmtpLine": "NA"
                }
            },
            "inbound-rtp": {
                "IT01A2890430182": {
                    "id": "IT01A2890430182",
                    "timestamp": "1690906102272",
                    "ssrc": "2890430182",
                    "kind": "audio",
                    "transportId": "T01",
                    "codecId": "CIT01_111_minptime=10;useinbandfec=1",
                    "packetsReceived": "88",
                    "packetsLost": "0",
                    "packetsDiscarded": "0",
                    "jitter": "0",
                    "bytesReceived": "3829",
                    "receiverId": "NA",
                    "remoteId": "NA",
                    "nackCount": "NA",
                    "audioLevel": "0",
                    "framesDecoded": "NA",
                    "framesReceived": "NA",
                    "framesDropped": "NA",
                    "partialFramesLost": "NA",
                    "totalAudioEnergy": "0",
                    "totalSamplesDuration": "1.7800000000000014"
                },
                "IT01V442805212": {
                    "id": "IT01V442805212",
                    "timestamp": "1690906102272",
                    "ssrc": "442805212",
                    "kind": "video",
                    "transportId": "T01",
                    "codecId": "CIT01_96",
                    "packetsReceived": "70",
                    "packetsLost": "0",
                    "packetsDiscarded": "NA",
                    "jitter": "0.001",
                    "bytesReceived": "39332",
                    "receiverId": "NA",
                    "remoteId": "NA",
                    "nackCount": "0",
                    "audioLevel": "NA",
                    "framesDecoded": "34",
                    "framesReceived": "34",
                    "framesDropped": "0",
                    "partialFramesLost": "NA",
                    "totalAudioEnergy": "NA",
                    "totalSamplesDuration": "NA"
                }
            },
            "local-candidate": {
                "IDWvHPefM": {
                    "id": "IDWvHPefM",
                    "timestamp": "1690906102272",
                    "address": "192.168.178.64",
                    "port": "51303",
                    "protocol": "udp",
                    "candidateType": "host",
                    "url": "NA"
                }
            },
            "outbound-rtp": {
                "OT01A3574048179": {
                    "id": "OT01A3574048179",
                    "timestamp": "1690906102272",
                    "ssrc": "3574048179",
                    "kind": "audio",
                    "transportId": "T01",
                    "codecId": "COT01_111_minptime=10;useinbandfec=1",
                    "packetsSent": "88",
                    "bytesSent": "3798",
                    "senderId": "NA",
                    "remoteId": "NA",
                    "nackCount": "0",
                    "framesEncoded": "NA",
                    "framesSent": "NA",
                    "framesPerSecond": "NA"
                },
                "OT01V2103595130": {
                    "id": "OT01V2103595130",
                    "timestamp": "1690906102272",
                    "ssrc": "2103595130",
                    "kind": "video",
                    "transportId": "T01",
                    "codecId": "COT01_96",
                    "packetsSent": "107",
                    "bytesSent": "91050",
                    "senderId": "NA",
                    "remoteId": "RIV2103595130",
                    "nackCount": "0",
                    "framesEncoded": "35",
                    "framesSent": "35",
                    "framesPerSecond": "20"
                }
            },
            "peer-connection": {
                "P": {
                    "id": "P",
                    "timestamp": "1690906102272",
                    "dataChannelsOpened": "1",
                    "dataChannelsClosed": "0"
                }
            },
            "remote-candidate": {
                "ICIqR60N3": {
                    "id": "ICIqR60N3",
                    "timestamp": "1690906102272",
                    "address": "94.34.153.239",
                    "port": "56253",
                    "protocol": "udp",
                    "candidateType": "srflx",
                    "url": "NA"
                },
                "Ib2xncI1j": {
                    "id": "Ib2xncI1j",
                    "timestamp": "1690906102272",
                    "address": "192.168.178.64",
                    "port": "56253",
                    "protocol": "udp",
                    "candidateType": "host",
                    "url": "NA"
                }
            },
            "transport": {
                "T01": {
                    "id": "T01",
                    "timestamp": "1690906102272",
                    "bytesSent": "105988",
                    "bytesReceived": "56109",
                    "selectedCandidatePairId": "CPDWvHPefM_b2xncI1j",
                    "localCertificateId": "CFD4:3D:28:22:F6:5D:CB:75:FE:DF:9D:16:AC:82:77:B1:48:0E:3A:9A:FD:B2:CD:C0:47:BB:E9:F7:B4:55:5C:B2",
                    "remoteCertificateId": "CF37:28:60:36:4C:68:4A:1F:89:A2:8F:90:AE:13:4E:D0:C8:4C:D7:E0:C8:CF:F4:3F:4D:71:F1:A0:2C:53:E8:47"
                }
            }
        },
        {
            "candidate-pair": {
                "CPDWvHPefM_CIqR60N3": {
                    "id": "CPDWvHPefM_CIqR60N3",
                    "timestamp": "1690906104410",
                    "localCandidateId": "IDWvHPefM",
                    "remoteCandidateId": "ICIqR60N3",
                    "state": "waiting",
                    "priority": "7241540810645060608",
                    "nominated": "false",
                    "bytesSent": "0",
                    "currentRoundTripTime": "NA",
                    "totalRoundTripTime": "0",
                    "bytesReceived": "0"
                },
                "CPDWvHPefM_b2xncI1j": {
                    "id": "CPDWvHPefM_b2xncI1j",
                    "timestamp": "1690906104410",
                    "localCandidateId": "IDWvHPefM",
                    "remoteCandidateId": "Ib2xncI1j",
                    "state": "succeeded",
                    "priority": "9115038255631186944",
                    "nominated": "true",
                    "bytesSent": "237570",
                    "currentRoundTripTime": "0.001",
                    "totalRoundTripTime": "0.008",
                    "bytesReceived": "120326"
                }
            },
            "codec": {
                "CIT01_111_minptime=10;useinbandfec=1": {
                    "id": "CIT01_111_minptime=10;useinbandfec=1",
                    "timestamp": "1690906104410",
                    "payloadType": "111",
                    "clockRate": "48000",
                    "channels": "2",
                    "codecType": "NA",
                    "mimeType": "audio/opus",
                    "sdpFmtpLine": "minptime=10;useinbandfec=1"
                },
                "CIT01_96": {
                    "id": "CIT01_96",
                    "timestamp": "1690906104410",
                    "payloadType": "96",
                    "clockRate": "90000",
                    "channels": "NA",
                    "codecType": "NA",
                    "mimeType": "video/VP8",
                    "sdpFmtpLine": "NA"
                },
                "COT01_111_minptime=10;useinbandfec=1": {
                    "id": "COT01_111_minptime=10;useinbandfec=1",
                    "timestamp": "1690906104410",
                    "payloadType": "111",
                    "clockRate": "48000",
                    "channels": "2",
                    "codecType": "NA",
                    "mimeType": "audio/opus",
                    "sdpFmtpLine": "minptime=10;useinbandfec=1"
                },
                "COT01_96": {
                    "id": "COT01_96",
                    "timestamp": "1690906104410",
                    "payloadType": "96",
                    "clockRate": "90000",
                    "channels": "NA",
                    "codecType": "NA",
                    "mimeType": "video/VP8",
                    "sdpFmtpLine": "NA"
                }
            },
            "inbound-rtp": {
                "IT01A2890430182": {
                    "id": "IT01A2890430182",
                    "timestamp": "1690906104410",
                    "ssrc": "2890430182",
                    "kind": "audio",
                    "transportId": "T01",
                    "codecId": "CIT01_111_minptime=10;useinbandfec=1",
                    "packetsReceived": "195",
                    "packetsLost": "0",
                    "packetsDiscarded": "0",
                    "jitter": "0",
                    "bytesReceived": "7426",
                    "receiverId": "NA",
                    "remoteId": "ROA2890430182",
                    "nackCount": "NA",
                    "audioLevel": "0",
                    "framesDecoded": "NA",
                    "framesReceived": "NA",
                    "framesDropped": "NA",
                    "partialFramesLost": "NA",
                    "totalAudioEnergy": "0",
                    "totalSamplesDuration": "3.9199999999999604"
                },
                "IT01V442805212": {
                    "id": "IT01V442805212",
                    "timestamp": "1690906104410",
                    "ssrc": "442805212",
                    "kind": "video",
                    "transportId": "T01",
                    "codecId": "CIT01_96",
                    "packetsReceived": "141",
                    "packetsLost": "0",
                    "packetsDiscarded": "NA",
                    "jitter": "0.001",
                    "bytesReceived": "91382",
                    "receiverId": "NA",
                    "remoteId": "NA",
                    "nackCount": "0",
                    "audioLevel": "NA",
                    "framesDecoded": "76",
                    "framesReceived": "77",
                    "framesDropped": "0",
                    "partialFramesLost": "NA",
                    "totalAudioEnergy": "NA",
                    "totalSamplesDuration": "NA"
                }
            },
            "local-candidate": {
                "IDWvHPefM": {
                    "id": "IDWvHPefM",
                    "timestamp": "1690906104410",
                    "address": "192.168.178.64",
                    "port": "51303",
                    "protocol": "udp",
                    "candidateType": "host",
                    "url": "NA"
                }
            },
            "outbound-rtp": {
                "OT01A3574048179": {
                    "id": "OT01A3574048179",
                    "timestamp": "1690906104410",
                    "ssrc": "3574048179",
                    "kind": "audio",
                    "transportId": "T01",
                    "codecId": "COT01_111_minptime=10;useinbandfec=1",
                    "packetsSent": "195",
                    "bytesSent": "6655",
                    "senderId": "NA",
                    "remoteId": "RIA3574048179",
                    "nackCount": "0",
                    "framesEncoded": "NA",
                    "framesSent": "NA",
                    "framesPerSecond": "NA"
                },
                "OT01V2103595130": {
                    "id": "OT01V2103595130",
                    "timestamp": "1690906104410",
                    "ssrc": "2103595130",
                    "kind": "video",
                    "transportId": "T01",
                    "codecId": "COT01_96",
                    "packetsSent": "236",
                    "bytesSent": "209269",
                    "senderId": "NA",
                    "remoteId": "RIV2103595130",
                    "nackCount": "0",
                    "framesEncoded": "77",
                    "framesSent": "77",
                    "framesPerSecond": "19"
                }
            },
            "peer-connection": {
                "P": {
                    "id": "P",
                    "timestamp": "1690906104410",
                    "dataChannelsOpened": "1",
                    "dataChannelsClosed": "0"
                }
            },
            "remote-candidate": {
                "ICIqR60N3": {
                    "id": "ICIqR60N3",
                    "timestamp": "1690906104410",
                    "address": "94.34.153.239",
                    "port": "56253",
                    "protocol": "udp",
                    "candidateType": "srflx",
                    "url": "NA"
                },
                "Ib2xncI1j": {
                    "id": "Ib2xncI1j",
                    "timestamp": "1690906104410",
                    "address": "192.168.178.64",
                    "port": "56253",
                    "protocol": "udp",
                    "candidateType": "host",
                    "url": "NA"
                }
            },
            "transport": {
                "T01": {
                    "id": "T01",
                    "timestamp": "1690906104410",
                    "bytesSent": "237570",
                    "bytesReceived": "120326",
                    "selectedCandidatePairId": "CPDWvHPefM_b2xncI1j",
                    "localCertificateId": "CFD4:3D:28:22:F6:5D:CB:75:FE:DF:9D:16:AC:82:77:B1:48:0E:3A:9A:FD:B2:CD:C0:47:BB:E9:F7:B4:55:5C:B2",
                    "remoteCertificateId": "CF37:28:60:36:4C:68:4A:1F:89:A2:8F:90:AE:13:4E:D0:C8:4C:D7:E0:C8:CF:F4:3F:4D:71:F1:A0:2C:53:E8:47"
                }
            }
        }
    ],
    "Network Profile": "",
    "Region Id": "NC",
    "Itinerary": "0"
}