
{
    "Connected": true,
    "Room": "https://falgsc.eu.org/#/pocPJ/228",
    "StatsArray": [
        {
            "candidate-pair": {
                "CP1zn+zuSE_Bdr60fp2": {
                    "id": "CP1zn+zuSE_Bdr60fp2",
                    "timestamp": "1691420588966",
                    "localCandidateId": "I1zn+zuSE",
                    "remoteCandidateId": "IBdr60fp2",
                    "state": "succeeded",
                    "priority": "9115038255631186944",
                    "nominated": "true",
                    "bytesSent": "80570",
                    "currentRoundTripTime": "0.001",
                    "totalRoundTripTime": "0.004",
                    "bytesReceived": "42684"
                },
                "CP1zn+zuSE_DDEWaoJk": {
                    "id": "CP1zn+zuSE_DDEWaoJk",
                    "timestamp": "1691420588966",
                    "localCandidateId": "I1zn+zuSE",
                    "remoteCandidateId": "IDDEWaoJk",
                    "state": "waiting",
                    "priority": "7241540810645060608",
                    "nominated": "false",
                    "bytesSent": "0",
                    "currentRoundTripTime": "NA",
                    "totalRoundTripTime": "0",
                    "bytesReceived": "0"
                }
            },
            "codec": {
                "CIT01_111_minptime=10;useinbandfec=1": {
                    "id": "CIT01_111_minptime=10;useinbandfec=1",
                    "timestamp": "1691420588966",
                    "payloadType": "111",
                    "clockRate": "48000",
                    "channels": "2",
                    "codecType": "NA",
                    "mimeType": "audio/opus",
                    "sdpFmtpLine": "minptime=10;useinbandfec=1"
                },
                "CIT01_96": {
                    "id": "CIT01_96",
                    "timestamp": "1691420588966",
                    "payloadType": "96",
                    "clockRate": "90000",
                    "channels": "NA",
                    "codecType": "NA",
                    "mimeType": "video/VP8",
                    "sdpFmtpLine": "NA"
                },
                "COT01_111_minptime=10;useinbandfec=1": {
                    "id": "COT01_111_minptime=10;useinbandfec=1",
                    "timestamp": "1691420588966",
                    "payloadType": "111",
                    "clockRate": "48000",
                    "channels": "2",
                    "codecType": "NA",
                    "mimeType": "audio/opus",
                    "sdpFmtpLine": "minptime=10;useinbandfec=1"
                },
                "COT01_96": {
                    "id": "COT01_96",
                    "timestamp": "1691420588966",
                    "payloadType": "96",
                    "clockRate": "90000",
                    "channels": "NA",
                    "codecType": "NA",
                    "mimeType": "video/VP8",
                    "sdpFmtpLine": "NA"
                }
            },
            "inbound-rtp": {
                "IT01A4274838266": {
                    "id": "IT01A4274838266",
                    "timestamp": "1691420588966",
                    "ssrc": "4274838266",
                    "kind": "audio",
                    "transportId": "T01",
                    "codecId": "CIT01_111_minptime=10;useinbandfec=1",
                    "packetsReceived": "65",
                    "packetsLost": "0",
                    "packetsDiscarded": "0",
                    "jitter": "0",
                    "bytesReceived": "4334",
                    "receiverId": "NA",
                    "remoteId": "NA",
                    "nackCount": "NA",
                    "audioLevel": "0",
                    "framesDecoded": "NA",
                    "framesReceived": "NA",
                    "framesDropped": "NA",
                    "partialFramesLost": "NA",
                    "totalAudioEnergy": "0",
                    "totalSamplesDuration": "1.360000000000001"
                },
                "IT01V24599055": {
                    "id": "IT01V24599055",
                    "timestamp": "1691420588966",
                    "ssrc": "24599055",
                    "kind": "video",
                    "transportId": "T01",
                    "codecId": "CIT01_96",
                    "packetsReceived": "48",
                    "packetsLost": "0",
                    "packetsDiscarded": "NA",
                    "jitter": "0",
                    "bytesReceived": "30246",
                    "receiverId": "NA",
                    "remoteId": "NA",
                    "nackCount": "0",
                    "audioLevel": "NA",
                    "framesDecoded": "24",
                    "framesReceived": "24",
                    "framesDropped": "0",
                    "partialFramesLost": "NA",
                    "totalAudioEnergy": "NA",
                    "totalSamplesDuration": "NA"
                }
            },
            "local-candidate": {
                "I1zn+zuSE": {
                    "id": "I1zn+zuSE",
                    "timestamp": "1691420588966",
                    "address": "192.168.178.64",
                    "port": "52007",
                    "protocol": "udp",
                    "candidateType": "host",
                    "url": "NA"
                }
            },
            "outbound-rtp": {
                "OT01A2486445656": {
                    "id": "OT01A2486445656",
                    "timestamp": "1691420588966",
                    "ssrc": "2486445656",
                    "kind": "audio",
                    "transportId": "T01",
                    "codecId": "COT01_111_minptime=10;useinbandfec=1",
                    "packetsSent": "65",
                    "bytesSent": "4406",
                    "senderId": "NA",
                    "remoteId": "NA",
                    "nackCount": "0",
                    "framesEncoded": "NA",
                    "framesSent": "NA",
                    "framesPerSecond": "NA"
                },
                "OT01V3832513296": {
                    "id": "OT01V3832513296",
                    "timestamp": "1691420588966",
                    "ssrc": "3832513296",
                    "kind": "video",
                    "transportId": "T01",
                    "codecId": "COT01_96",
                    "packetsSent": "82",
                    "bytesSent": "66060",
                    "senderId": "NA",
                    "remoteId": "RIV3832513296",
                    "nackCount": "0",
                    "framesEncoded": "25",
                    "framesSent": "25",
                    "framesPerSecond": "20"
                }
            },
            "peer-connection": {
                "P": {
                    "id": "P",
                    "timestamp": "1691420588966",
                    "dataChannelsOpened": "1",
                    "dataChannelsClosed": "0"
                }
            },
            "remote-candidate": {
                "IBdr60fp2": {
                    "id": "IBdr60fp2",
                    "timestamp": "1691420588966",
                    "address": "192.168.178.64",
                    "port": "55030",
                    "protocol": "udp",
                    "candidateType": "host",
                    "url": "NA"
                },
                "IDDEWaoJk": {
                    "id": "IDDEWaoJk",
                    "timestamp": "1691420588966",
                    "address": "62.10.73.22",
                    "port": "55030",
                    "protocol": "udp",
                    "candidateType": "srflx",
                    "url": "NA"
                }
            },
            "transport": {
                "T01": {
                    "id": "T01",
                    "timestamp": "1691420588966",
                    "bytesSent": "80570",
                    "bytesReceived": "42684",
                    "selectedCandidatePairId": "CP1zn+zuSE_Bdr60fp2",
                    "localCertificateId": "CFC1:6A:49:4F:8D:08:4D:62:8B:4D:D0:66:69:E4:6F:C4:25:57:AB:E6:FE:B4:F2:EC:D2:0C:94:FE:82:77:BD:06",
                    "remoteCertificateId": "CF96:4B:99:69:B7:5D:2B:7C:14:34:50:2F:D7:A2:52:D1:3B:F2:08:F5:41:A0:78:EC:4F:CB:6E:6B:B5:D5:47:B3"
                }
            }
        },
        {
            "candidate-pair": {
                "CP1zn+zuSE_Bdr60fp2": {
                    "id": "CP1zn+zuSE_Bdr60fp2",
                    "timestamp": "1691420591047",
                    "localCandidateId": "I1zn+zuSE",
                    "remoteCandidateId": "IBdr60fp2",
                    "state": "succeeded",
                    "priority": "9115038255631186944",
                    "nominated": "true",
                    "bytesSent": "215197",
                    "currentRoundTripTime": "0",
                    "totalRoundTripTime": "0.004",
                    "bytesReceived": "108378"
                },
                "CP1zn+zuSE_DDEWaoJk": {
                    "id": "CP1zn+zuSE_DDEWaoJk",
                    "timestamp": "1691420591047",
                    "localCandidateId": "I1zn+zuSE",
                    "remoteCandidateId": "IDDEWaoJk",
                    "state": "waiting",
                    "priority": "7241540810645060608",
                    "nominated": "false",
                    "bytesSent": "0",
                    "currentRoundTripTime": "NA",
                    "totalRoundTripTime": "0",
                    "bytesReceived": "0"
                }
            },
            "codec": {
                "CIT01_111_minptime=10;useinbandfec=1": {
                    "id": "CIT01_111_minptime=10;useinbandfec=1",
                    "timestamp": "1691420591047",
                    "payloadType": "111",
                    "clockRate": "48000",
                    "channels": "2",
                    "codecType": "NA",
                    "mimeType": "audio/opus",
                    "sdpFmtpLine": "minptime=10;useinbandfec=1"
                },
                "CIT01_96": {
                    "id": "CIT01_96",
                    "timestamp": "1691420591047",
                    "payloadType": "96",
                    "clockRate": "90000",
                    "channels": "NA",
                    "codecType": "NA",
                    "mimeType": "video/VP8",
                    "sdpFmtpLine": "NA"
                },
                "COT01_111_minptime=10;useinbandfec=1": {
                    "id": "COT01_111_minptime=10;useinbandfec=1",
                    "timestamp": "1691420591047",
                    "payloadType": "111",
                    "clockRate": "48000",
                    "channels": "2",
                    "codecType": "NA",
                    "mimeType": "audio/opus",
                    "sdpFmtpLine": "minptime=10;useinbandfec=1"
                },
                "COT01_96": {
                    "id": "COT01_96",
                    "timestamp": "1691420591047",
                    "payloadType": "96",
                    "clockRate": "90000",
                    "channels": "NA",
                    "codecType": "NA",
                    "mimeType": "video/VP8",
                    "sdpFmtpLine": "NA"
                }
            },
            "inbound-rtp": {
                "IT01A4274838266": {
                    "id": "IT01A4274838266",
                    "timestamp": "1691420591047",
                    "ssrc": "4274838266",
                    "kind": "audio",
                    "transportId": "T01",
                    "codecId": "CIT01_111_minptime=10;useinbandfec=1",
                    "packetsReceived": "169",
                    "packetsLost": "0",
                    "packetsDiscarded": "0",
                    "jitter": "0",
                    "bytesReceived": "11143",
                    "receiverId": "NA",
                    "remoteId": "ROA4274838266",
                    "nackCount": "NA",
                    "audioLevel": "0",
                    "framesDecoded": "NA",
                    "framesReceived": "NA",
                    "framesDropped": "NA",
                    "partialFramesLost": "NA",
                    "totalAudioEnergy": "0",
                    "totalSamplesDuration": "3.4399999999999706"
                },
                "IT01V24599055": {
                    "id": "IT01V24599055",
                    "timestamp": "1691420591047",
                    "ssrc": "24599055",
                    "kind": "video",
                    "transportId": "T01",
                    "codecId": "CIT01_96",
                    "packetsReceived": "116",
                    "packetsLost": "0",
                    "packetsDiscarded": "NA",
                    "jitter": "0",
                    "bytesReceived": "80877",
                    "receiverId": "NA",
                    "remoteId": "NA",
                    "nackCount": "0",
                    "audioLevel": "NA",
                    "framesDecoded": "66",
                    "framesReceived": "66",
                    "framesDropped": "0",
                    "partialFramesLost": "NA",
                    "totalAudioEnergy": "NA",
                    "totalSamplesDuration": "NA"
                }
            },
            "local-candidate": {
                "I1zn+zuSE": {
                    "id": "I1zn+zuSE",
                    "timestamp": "1691420591047",
                    "address": "192.168.178.64",
                    "port": "52007",
                    "protocol": "udp",
                    "candidateType": "host",
                    "url": "NA"
                }
            },
            "outbound-rtp": {
                "OT01A2486445656": {
                    "id": "OT01A2486445656",
                    "timestamp": "1691420591047",
                    "ssrc": "2486445656",
                    "kind": "audio",
                    "transportId": "T01",
                    "codecId": "COT01_111_minptime=10;useinbandfec=1",
                    "packetsSent": "169",
                    "bytesSent": "11200",
                    "senderId": "NA",
                    "remoteId": "RIA2486445656",
                    "nackCount": "0",
                    "framesEncoded": "NA",
                    "framesSent": "NA",
                    "framesPerSecond": "NA"
                },
                "OT01V3832513296": {
                    "id": "OT01V3832513296",
                    "timestamp": "1691420591047",
                    "ssrc": "3832513296",
                    "kind": "video",
                    "transportId": "T01",
                    "codecId": "COT01_96",
                    "packetsSent": "209",
                    "bytesSent": "183681",
                    "senderId": "NA",
                    "remoteId": "RIV3832513296",
                    "nackCount": "0",
                    "framesEncoded": "67",
                    "framesSent": "67",
                    "framesPerSecond": "20"
                }
            },
            "peer-connection": {
                "P": {
                    "id": "P",
                    "timestamp": "1691420591047",
                    "dataChannelsOpened": "1",
                    "dataChannelsClosed": "0"
                }
            },
            "remote-candidate": {
                "IBdr60fp2": {
                    "id": "IBdr60fp2",
                    "timestamp": "1691420591047",
                    "address": "192.168.178.64",
                    "port": "55030",
                    "protocol": "udp",
                    "candidateType": "host",
                    "url": "NA"
                },
                "IDDEWaoJk": {
                    "id": "IDDEWaoJk",
                    "timestamp": "1691420591047",
                    "address": "62.10.73.22",
                    "port": "55030",
                    "protocol": "udp",
                    "candidateType": "srflx",
                    "url": "NA"
                }
            },
            "transport": {
                "T01": {
                    "id": "T01",
                    "timestamp": "1691420591047",
                    "bytesSent": "215197",
                    "bytesReceived": "108378",
                    "selectedCandidatePairId": "CP1zn+zuSE_Bdr60fp2",
                    "localCertificateId": "CFC1:6A:49:4F:8D:08:4D:62:8B:4D:D0:66:69:E4:6F:C4:25:57:AB:E6:FE:B4:F2:EC:D2:0C:94:FE:82:77:BD:06",
                    "remoteCertificateId": "CF96:4B:99:69:B7:5D:2B:7C:14:34:50:2F:D7:A2:52:D1:3B:F2:08:F5:41:A0:78:EC:4F:CB:6E:6B:B5:D5:47:B3"
                }
            }
        }
    ],
    "Network Profile": "",
    "Region Id": "NC",
    "Itinerary": "0"
}